fastapi_responses/__init__.py
fastapi_responses/openapi.py
fastapi_responses/utils.py
fastapi_responses-0.2.0.dist-info/LICENSE
fastapi_responses-0.2.0.dist-info/WHEEL
fastapi_responses-0.2.0.dist-info/METADATA
fastapi_responses-0.2.0.dist-info/RECORD
